{"network_id": "9ecaf753-28a0-11e8-9c1a-525400c25d22", "ndex": "http://dev.ndexbio.org", "e_set": "pipeline", "name": "COREGULATION OF ANDROGEN RECEPTOR ACTIVITY", "ids": ["CCND1", "FHL2", "CMTM2", "CCND3", "BRCA1P1", "PRKDC", "SVIL", "AR", "UBA3", "ZMIZ1", "FKBPL", "AKT1", "MBD4", "CDKN2A-DT", "VAV3", "UBE2I", "NCOA4", "ALPK3", "CDK11B", "HIP1", "PAWR", "KDM4C", "PATZ1", "TCF7L2", "NKX3-1", "PIAS3", "CASP8", "PIAS1", "NRIP1", "UBE3A", "XRCC5", "CDK6", "SPATA6", "SNURF", "ZNF318", "KDM1A", "TGIF1", "PELP1", "TMF1", "KDM3A", "APPL1", "TMPRSS2", "RPS6KA3", "KLK3", "LATS2", "PRDX1", "XRCC6", "NCOA6", "CARM1", "CTDSP1", "HNRNPA1", "NCOA2", "CTDSP2", "TGFB1I1", "GSN", "PTK2B", "CTNNB1", "PA2G4", "PIAS4", "RANBP9", "KLK2"]}