{"network_id": "a4a6554d-28a1-11e8-9c1a-525400c25d22", "ndex": "http://dev.ndexbio.org", "e_set": "pipeline", "name": "REGULATION OF RAC1 ACTIVITY", "ids": ["TIAM1", "VAV3", "ABI1", "ARHGAP9", "RACGAP1", "ARHGEF25", "ELMO1", "ABR", "ARHGAP32", "CHN1", "DOCK2", "ARHGEF6", "DOCK1", "MCF2", "KALRN", "VAV2", "ARHGAP1", "PREX1", "DOCK6", "TIAM2", "ARHGDIA", "DEFA6", "RNASE1", "NGEF", "SPATA13", "RASGRF2", "RAP1GDS1", "RASGRF1", "ARHGEF7", "RALBP1", "ARHGEF2", "GCH1", "PREX2", "ARHGAP17", "EPS8", "TRIO", "BCRP2", "VAV1", "SOS1", "CHN2"]}