{"network_id": "f2823d44-28a0-11e8-9c1a-525400c25d22", "ndex": "http://dev.ndexbio.org", "e_set": "pipeline", "name": "IL8- AND CXCR2-MEDIATED SIGNALING EVENTS", "ids": ["GNG2", "CXCR2", "VTRNA2-1", "MTG1", "RAB5A", "PRKCB", "PLCB1", "ELMO1", "PLCB2", "AKT1", "GNA15", "DOCK2", "HCK", "DAG1", "RAB11A", "GNB1", "VASP", "PRKCG", "FGR", "RAC2", "GNAI2", "RAB7A", "GCH1", "CXCL8", "ARRB2", "PIK3R6", "PDPK1", "PLD2", "PPP2R1A", "PIK3CG", "ARRB1", "LYN", "PLCB3", "PPP2CA", "PYCARD", "PRKCA", "DNM1", "GNA14"]}